sncf/__init__.py
sncf/train_traveler.py
sncf/connections/__init__.py
sncf/connections/connection_manager.py
sncf/entities/__init__.py
sncf/entities/disruption_entity.py
sncf/entities/entity_manager.py
sncf/entities/information_entity.py
sncf/entities/journey_entity.py
sncf/entities/line_entity.py
sncf/entities/link_entity.py
sncf/entities/place_entity.py
sncf/entities/public_transport_entity.py
sncf/entities/stop_date_time_entity.py
sncf/entities/stop_entity.py
sncf/models/__init__.py
sncf/models/area_model.py
sncf/models/journey_model.py
sncf/models/next_journey_model.py
sncf/repositories/__init__.py
sncf/repositories/disruption_repository.py
sncf/repositories/journey_repository.py
sncf/repositories/line_repository.py
sncf/repositories/link_repository.py
sncf/repositories/place_repository.py
sncf/repositories/repository_manager.py
sncf/repositories/stop_area_repository.py
sncf/repositories/stop_point_repository.py
sncf/services/__init__.py
sncf/services/area_service.py
sncf/services/info_service.py
sncf/services/journey_service.py
sncf/services/service_manager.py
train_traveler_api-0.1.0a1716738338.dist-info/LICENSE
train_traveler_api-0.1.0a1716738338.dist-info/METADATA
train_traveler_api-0.1.0a1716738338.dist-info/WHEEL
train_traveler_api-0.1.0a1716738338.dist-info/entry_points.txt
train_traveler_api-0.1.0a1716738338.dist-info/top_level.txt
train_traveler_api-0.1.0a1716738338.dist-info/RECORD
