Metadata-Version: 2.1
Name: train-traveler-api
Version: 0.1.0a1716738338
Summary: Train traveler is a backend for SNCF API
Home-page: https://github.com/Matthyeux/train-traveler-api
Author: Matthieu DURINDEL
License: MIT
Classifier: Programming Language :: Python :: 3
Classifier: License :: OSI Approved :: MIT License
Classifier: Operating System :: OS Independent
License-File: LICENSE
